binary_ti_gray/code+testbench/design.v
module b2g(
    input [3 :0] binary,
    output [3:0] gray
);
assign gray[3] = binary[3];
assign gray[2] = binary[3] ^ binary[2];
assign gray[1] = binary[2] ^ binary[1];
assign gray[0] = binary[1] ^ binary[0];

endmodule

binary_ti_gray/code+testbench/testbench.v
module the_testbench;
     reg [3:0] binary;
     wire [3:0] gray;


     b2g uut(
        .binary(binary),
        .gray(gray)
     );

     initial begin
       $dumpfile("dump.vcd");
       $dumpvars(0,the_testbench);

       binary = 4'b0000;
       #100;
        binary = 4'b0001;
       #100;
        binary = 4'b0010;
       #100;
        binary = 4'b0011;
       #100;
        binary = 4'b0100;
       #100;
        binary = 4'b0101;
       #100;
        binary = 4'b0110;
       #100;
        binary = 4'b0111;
       #100;
        binary = 4'b1000;
       #100;
        binary = 4'b1001;
       #100;
        binary = 4'b1010;
       #100;
        binary = 4'b1011;
       #100;
        binary = 4'b1100;
       #100;
        binary = 4'b1101;
       #100;
        binary = 4'b1110;
       #100;
        binary = 4'b1111;
       #100;
       $finish;


     end
endmodule

binary_ti_gray/vcd&vvp_files/dump.vcd
$date
	Fri Aug 30 20:48:39 2024
$end
$version
	Icarus Verilog
$end
$timescale
	1s
$end
$scope module the_testbench $end
$var wire 4 ! gray [3:0] $end
$var reg 4 " binary [3:0] $end
$scope module uut $end
$var wire 4 # binary [3:0] $end
$var wire 4 $ gray [3:0] $end
$upscope $end
$upscope $end
$enddefinitions $end
#0
$dumpvars
b0 $
b0 #
b0 "
b0 !
$end
#100
b1 !
b1 $
b1 "
b1 #
#200
b11 !
b11 $
b10 "
b10 #
#300
b10 !
b10 $
b11 "
b11 #
#400
b110 !
b110 $
b100 "
b100 #
#500
b111 !
b111 $
b101 "
b101 #
#600
b101 !
b101 $
b110 "
b110 #
#700
b100 !
b100 $
b111 "
b111 #
#800
b1100 !
b1100 $
b1000 "
b1000 #
#900
b1101 !
b1101 $
b1001 "
b1001 #
#1000
b1111 !
b1111 $
b1010 "
b1010 #
#1100
b1110 !
b1110 $
b1011 "
b1011 #
#1200
b1010 !
b1010 $
b1100 "
b1100 #
#1300
b1011 !
b1011 $
b1101 "
b1101 #
#1400
b1001 !
b1001 $
b1110 "
b1110 #
#1500
b1000 !
b1000 $
b1111 "
b1111 #
